freekmapper/__init__.py
freekmapper/control_panel.py
freekmapper/engine.py
freekmapper/main.py
freekmapper/media_loader.py
freekmapper/renderers.py
freekmapper/repro_texture.py
freekmapper/repro_texture_dpg.py
freekmapper/sequence_setup.py
freekmapper/surface.py
freekmapper/video_source.py
freekmapper-0.1.4.dist-info/licenses/LICENSE
freekmapper-0.1.4.dist-info/METADATA
freekmapper-0.1.4.dist-info/WHEEL
freekmapper-0.1.4.dist-info/entry_points.txt
freekmapper-0.1.4.dist-info/top_level.txt
freekmapper-0.1.4.dist-info/RECORD
