Metadata-Version: 2.4
Name: freekmapper
Version: 0.1.4
Summary: A projection mapping application using PyOpenGL and Tkinter
Author: Vishal Rajendra Kumar
License: MIT License
Requires-Python: >=3.8
License-File: LICENSE
Requires-Dist: moderngl
Requires-Dist: glfw
Requires-Dist: dearpygui
Requires-Dist: opencv-python
Requires-Dist: numpy
Requires-Dist: Pillow
Requires-Dist: sv-ttk
Requires-Dist: pyopengltk
Dynamic: license-file
